setup.py
codalib/__init__.py
codalib/anvl.py
codalib/bagatom.py
codalib/util.py
codalib.egg-info/PKG-INFO
codalib.egg-info/SOURCES.txt
codalib.egg-info/dependency_links.txt
codalib.egg-info/not-zip-safe
codalib.egg-info/pbr.json
codalib.egg-info/requires.txt
codalib.egg-info/top_level.txt
tests/__init__.py
tests/test_anvl.py
tests/bagatom/__init__.py
tests/bagatom/test_bagToXML.py
tests/bagatom/test_getters.py
tests/bagatom/test_makeServiceDocXML.py
tests/bagatom/test_nodeToXML.py
tests/bagatom/test_queueEntryToXML.py
tests/bagatom/test_updateObjectFromXML.py
tests/bagatom/test_wrapAtom.py
tests/util/__init__.py
tests/util/test_createPREMISEventXML.py
tests/util/test_deleteQueue.py
tests/util/test_doWaitWebRequest.py
tests/util/test_doWebRequest.py
tests/util/test_parseVocabularySources.py
tests/util/test_requests.py
tests/util/test_sendPREMISEvent.py
tests/util/test_updateQueue.py
tests/util/test_waitForURL.py