Metadata-Version: 1.1
Name: codalib
Version: 1.0.0
Summary: A helper library for Coda.
Home-page: https://github.com/unt-libraries/codalib
Author: University of North Texas Libraries
Author-email: mark.phillips@unt.edu
License: BSD
Keywords: library anvl coda
Platform: UNKNOWN
Classifier: Intended Audience :: Developers
Classifier: Natural Language :: English
Classifier: Programming Language :: Python
Classifier: Programming Language :: Python :: 2.7
